rubies/__init__.py
rubies/decoder_auto.py
rubies/decoder_base.py
rubies/decoder_simple.py
rubies/encoder.py
rubies/extractor.py
rubies/plotter.py
rubies/utils.py
rubies-1.0.1.dist-info/LICENSE
rubies-1.0.1.dist-info/METADATA
rubies-1.0.1.dist-info/WHEEL
rubies-1.0.1.dist-info/top_level.txt
rubies-1.0.1.dist-info/RECORD
