Metadata-Version: 2.1
Name: rubies
Version: 1.0.1
Summary: A steganography tool for hiding two images into one image.
Home-page: https://github.com/electricalgorithm/rubies-steganography
Author: Gökhan Koçmarlı
Author-email: gokhan.kocmarli@gmail.com
Project-URL: Bug Tracker, https://github.com/electricalgorithm/rubies-steganography/issues
Project-URL: repository, https://github.com/electricalgorithm/rubies-steganography
Classifier: Programming Language :: Python :: 3
Classifier: License :: OSI Approved :: GNU General Public License v3 (GPLv3)
Classifier: Operating System :: OS Independent
Classifier: Topic :: Scientific/Engineering :: Image Processing
Classifier: Topic :: Security
Requires-Python: >=3.6
License-File: LICENSE
Requires-Dist: matplotlib
Requires-Dist: numpy
Requires-Dist: opencv-python
